{"DocumentConnection":{"type":"DocumentConnection","resolveType":"multiCollectionDocumentList","collections":["payment"]},"Node":{"type":"Node","resolveType":"nodeDocument"},"DocumentNode":{"type":"DocumentNode","resolveType":"multiCollectionDocument","createDocument":"create","updateDocument":"update"},"Payment":{"type":"Payment","resolveType":"collectionDocument","collection":"payment","createPayment":"create","updatePayment":"update"},"PaymentConnection":{"type":"PaymentConnection","resolveType":"collectionDocumentList","collection":"payment"}}